factorizer.cpython-38-x86_64-linux-gnu.so
factorizer-0.9.6.dist-info/LICENSE
factorizer-0.9.6.dist-info/METADATA
factorizer-0.9.6.dist-info/WHEEL
factorizer-0.9.6.dist-info/top_level.txt
factorizer-0.9.6.dist-info/RECORD
