Metadata-Version: 2.1
Name: factorizer
Version: 0.9.6
Summary: UNKNOWN
Home-page: https://github.com/FullteaOfEEIC/factorizer
Author: Fulltea
Author-email: rikuta@furutan.com
License: UNKNOWN
Platform: UNKNOWN
License-File: LICENSE
Requires-Dist: cython (>=0.29)
Requires-Dist: requests
Requires-Dist: setuptools (>=60.5)
